mcp_ssh_vps-0.7.0.dist-info/licenses/LICENSE
sshmcp/__init__.py
sshmcp/cli.py
sshmcp/config.py
sshmcp/server.py
sshmcp/core/__init__.py
sshmcp/core/container.py
sshmcp/models/__init__.py
sshmcp/models/command.py
sshmcp/models/file.py
sshmcp/models/machine.py
sshmcp/monitoring/__init__.py
sshmcp/monitoring/alerts.py
sshmcp/prompts/__init__.py
sshmcp/prompts/backup.py
sshmcp/prompts/deploy.py
sshmcp/prompts/monitor.py
sshmcp/resources/__init__.py
sshmcp/resources/logs.py
sshmcp/resources/metrics.py
sshmcp/resources/status.py
sshmcp/security/__init__.py
sshmcp/security/audit.py
sshmcp/security/rate_limiter.py
sshmcp/security/totp.py
sshmcp/security/validator.py
sshmcp/security/whitelist.py
sshmcp/ssh/__init__.py
sshmcp/ssh/async_client.py
sshmcp/ssh/client.py
sshmcp/ssh/executor.py
sshmcp/ssh/forwarding.py
sshmcp/ssh/pool.py
sshmcp/ssh/shell.py
sshmcp/ssh/transfer.py
sshmcp/tools/__init__.py
sshmcp/tools/commands.py
sshmcp/tools/files.py
sshmcp/tools/formatter.py
sshmcp/tools/helpers.py
sshmcp/tools/history.py
sshmcp/tools/processes.py
sshmcp/tools/servers.py
sshmcp/ws/__init__.py
sshmcp/ws/shell.py
mcp_ssh_vps-0.7.0.dist-info/METADATA
mcp_ssh_vps-0.7.0.dist-info/WHEEL
mcp_ssh_vps-0.7.0.dist-info/entry_points.txt
mcp_ssh_vps-0.7.0.dist-info/top_level.txt
mcp_ssh_vps-0.7.0.dist-info/RECORD
