Metadata-Version: 2.4
Name: mcp-ssh-vps
Version: 0.7.0
Summary: MCP server for managing VPS via SSH - gives AI agents secure access to remote servers
Author-email: LuxVTZ <luxvtz@example.com>
Maintainer: LuxVTZ
License: MIT
Project-URL: Homepage, https://github.com/LuxVTZ/sshmcp
Project-URL: Documentation, https://github.com/LuxVTZ/sshmcp#readme
Project-URL: Repository, https://github.com/LuxVTZ/sshmcp
Project-URL: Issues, https://github.com/LuxVTZ/sshmcp/issues
Keywords: mcp,ssh,vps,ai,automation,claude,llm,model-context-protocol
Classifier: Development Status :: 3 - Alpha
Classifier: Intended Audience :: Developers
Classifier: License :: OSI Approved :: MIT License
Classifier: Operating System :: OS Independent
Classifier: Programming Language :: Python :: 3
Classifier: Programming Language :: Python :: 3.10
Classifier: Programming Language :: Python :: 3.11
Classifier: Programming Language :: Python :: 3.12
Classifier: Programming Language :: Python :: 3.13
Classifier: Topic :: System :: Systems Administration
Requires-Python: >=3.10
License-File: LICENSE
Requires-Dist: mcp>=1.0.0
Requires-Dist: pydantic>=2.0.0
Requires-Dist: paramiko>=3.0.0
Requires-Dist: structlog>=24.0.0
Requires-Dist: python-dotenv>=1.0.0
Requires-Dist: click>=8.0.0
Provides-Extra: dev
Requires-Dist: pytest>=8.0.0; extra == "dev"
Requires-Dist: pytest-asyncio>=0.24.0; extra == "dev"
Requires-Dist: pytest-mock>=3.14.0; extra == "dev"
Requires-Dist: pytest-cov>=4.0.0; extra == "dev"
Requires-Dist: black>=24.0.0; extra == "dev"
Requires-Dist: ruff>=0.8.0; extra == "dev"
Requires-Dist: mypy>=1.13.0; extra == "dev"
Provides-Extra: totp
Requires-Dist: pyotp>=2.9.0; extra == "totp"
Requires-Dist: qrcode>=7.0; extra == "totp"
Provides-Extra: docs
Requires-Dist: mkdocs>=1.5.0; extra == "docs"
Requires-Dist: mkdocs-material>=9.5.0; extra == "docs"
Requires-Dist: pymdown-extensions>=10.0.0; extra == "docs"
Dynamic: license-file
